hygraph_core/HyGraphFileLoaderBatch.py
hygraph_core/__init__.py
hygraph_core/constraints.py
hygraph_core/construct_graph.py
hygraph_core/fileProcessing.py
hygraph_core/generator.py
hygraph_core/graph_operators.py
hygraph_core/hygraph.py
hygraph_core/hygraph_csv_loader.py
hygraph_core/hygraph_import_json.py
hygraph_core/hygraph_json_loader.py
hygraph_core/hygraph_loader_base.py
hygraph_core/hygraph_universal_pipeline.py
hygraph_core/idGenerator.py
hygraph_core/main.py
hygraph_core/oberserver.py
hygraph_core/subgraph_metric.py
hygraph_core/timeseries_operators.py
hygraph_core/utils.py
hygraph_core/inputFiles/__init__.py
hygraph_core/inputFiles/custom_aggregation_functions.py
tests/__init__.py
tests/tes_file_upload.py
tests/testBasic.py
tests/test_TSExtract.py
tests/test_hygraph.py
tests/test_queries.py
hygraph_core-0.3.9.9.dist-info/LICENSE
hygraph_core-0.3.9.9.dist-info/METADATA
hygraph_core-0.3.9.9.dist-info/WHEEL
hygraph_core-0.3.9.9.dist-info/top_level.txt
hygraph_core-0.3.9.9.dist-info/RECORD
