Metadata-Version: 2.1
Name: hygraph_core
Version: 0.3.9.9
Summary: A package for managing and analyzing HyGraph data
Home-page: https://github.com/
Author: Mouna
Author-email: 
Classifier: Programming Language :: Python :: 3
Classifier: License :: OSI Approved :: MIT License
Classifier: Operating System :: OS Independent
Requires-Python: >=3.6
License-File: LICENSE
Requires-Dist: numpy
Requires-Dist: pandas
Requires-Dist: xarray
Requires-Dist: scipy
Requires-Dist: fastdtw
Requires-Dist: networkx
Requires-Dist: matplotlib
Requires-Dist: scikit-learn
Requires-Dist: igraph
Requires-Dist: statsmodels
Requires-Dist: ijson
Requires-Dist: polars
